{
  "type": "root",
  "children": [
    {
      "type": "code",
      "lang": "svelte",
      "meta": null,
      "value": "<script>\n  const msg = 'world!' // [svp! hl]\n</script>\n  \n<h1>\n  Hello, {msg}\n</h1>",
      "position": {
        "start": {
          "line": 1,
          "column": 1,
          "offset": 0
        },
        "end": {
          "line": 9,
          "column": 4,
          "offset": 97
        }
      }
    }
  ],
  "position": {
    "start": {
      "line": 1,
      "column": 1,
      "offset": 0
    },
    "end": {
      "line": 9,
      "column": 4,
      "offset": 97
    }
  }
}